mzerror/__init__.py
mzerror/error_handler.py
mzerror/mysql_connection.py
mzerror-0.1.3.dist-info/LICENSE
mzerror-0.1.3.dist-info/METADATA
mzerror-0.1.3.dist-info/WHEEL
mzerror-0.1.3.dist-info/top_level.txt
mzerror-0.1.3.dist-info/RECORD
